deployer/__init__.py
deployer/_repo.py
deployer/logging.yaml
deployer/pxd.py
deployer/version.txt
deployer/config/__init__.py
deployer/config/config.py
deployer/config/log_config.py
deployer/config/metadb_config.py
deployer/constant/__init__.py
deployer/constant/constant.py
deployer/constant/table_field.py
deployer/core/__init__.py
deployer/core/context.py
deployer/core/docker_manager.py
deployer/core/file_manager.py
deployer/core/flow.py
deployer/decorator/__init__.py
deployer/decorator/decorators.py
deployer/download/__init__.py
deployer/download/constant.py
deployer/download/polardbx_download.py
deployer/pcn/__init__.py
deployer/pxc/__init__.py
deployer/pxc/gms_consts.py
deployer/pxc/polardbx_cluster.py
deployer/pxc/polardbx_manager.py
deployer/pxc/polardbx_topology.py
deployer/pxc/pxc_user.py
deployer/resources/__init__.py
deployer/resources/download/scripts/load_image.sh
deployer/resources/download/scripts/polardbx-version.sh
deployer/resources/sql/gms_init.sql
deployer/resources/sql/sqlite_init.sql
deployer/resources/template/my-8.0.cnf
deployer/resources/template/my.cnf
deployer/resources/template/my.cnf-5.7
deployer/resources/template/my.cnf-5.7-xcluster
deployer/resources/template/my.cnf-8.0-galaxy
deployer/resources/template/my.cnf-8.0-xcluster
deployer/sqlite/__init__.py
deployer/sqlite/dbapi.py
deployer/sqlite/sqlite_manager.py
deployer/tests/__init__.py
deployer/tryout/__init__.py
deployer/tryout/install.py
deployer/util/__init__.py
deployer/util/file_manager.py
deployer/util/mysql_manager.py
deployer/util/network_util.py
deployer/util/password_util.py
deployer/util/sqlite_manager.py
deployer/util/yaml_util.py
deployer/xdb/__init__.py
deployer/xdb/xdb.py
pxd-0.7.1.dist-info/LICENSE
pxd-0.7.1.dist-info/METADATA
pxd-0.7.1.dist-info/WHEEL
pxd-0.7.1.dist-info/entry_points.txt
pxd-0.7.1.dist-info/top_level.txt
pxd-0.7.1.dist-info/RECORD
