Metadata-Version: 2.1
Name: pxd
Version: 0.7.1
Summary: This is a tool to download and install PolarDB-X
Author: polardbx
Author-email: vettal.wd@alibaba-inc.com
Platform: all
Classifier: Programming Language :: Python
Classifier: Programming Language :: Python :: 3
Classifier: Programming Language :: Python :: 3.5
Classifier: Programming Language :: Python :: 3.6
Classifier: Programming Language :: Python :: 3.7
Classifier: Programming Language :: Python :: 3.8
Classifier: License :: OSI Approved :: Apache Software License
Classifier: Operating System :: OS Independent
License-File: LICENSE
Requires-Dist: certifi (==2021.5.30)
Requires-Dist: charset-normalizer (==2.0.4)
Requires-Dist: click (==8.0.1)
Requires-Dist: docker (==5.0.0)
Requires-Dist: idna (==3.2)
Requires-Dist: colorama (==0.4.4)
Requires-Dist: pycryptodomex (==3.10.1)
Requires-Dist: PyMySQL (==1.0.2)
Requires-Dist: PyYAML (==5.4.1)
Requires-Dist: requests (==2.26.0)
Requires-Dist: retrying (==1.3.3)
Requires-Dist: six (==1.16.0)
Requires-Dist: urllib3 (==1.26.6)
Requires-Dist: websocket-client (==1.2.1)
Requires-Dist: spurplus (==2.3.4)
Requires-Dist: humanfriendly (==10.0)
Requires-Dist: packaging (>=21.0)
